System/Archivebaldweg/Pylovara/MCSVerilog/Proteine/mcs_protein.v
module mcs_protein (
    input wire clk,
    input wire [7:0] cmd_in,
    input wire [31:0] src_addr_in,
    input wire [31:0] dst_addr_in,
    input wire [7:0] data_in,
    output reg [7:0] data_out,
    output reg [31:0] src_addr_out,
    output reg [31:0] dst_addr_out,
    input wire executable,
    output reg valid
);

    parameter STATE_IDLE  = 3'b000;
    parameter STATE_CMD   = 3'b001;
    parameter STATE_SRC   = 3'b010;
    parameter STATE_DST   = 3'b011;
    parameter STATE_SYNC  = 3'b100;
    reg [2:0] state = STATE_IDLE; // 2:0=5 zustände 3:0=16 zustände

    reg [7:0] cmd_reg = 8'b00000000;
    reg [31:0] src_addr_reg = 32'h00000000;
    reg [31:0] dst_addr_reg = 32'h00000000;

    always @(posedge clk) begin
        case (state)
            STATE_IDLE: begin
                valid <= 0;
                if (cmd_in != 8'b00000000) begin
                    cmd_reg <= cmd_in;
                    if (src_addr_in != 32'h00000000) src_addr_reg <= src_addr_in;
                    if (dst_addr_in != 32'h00000000) dst_addr_reg <= dst_addr_in;
                    state <= STATE_DST;
                end
            end
            STATE_DST: begin
                if (executable) begin
                    if (cmd_reg == 8'b00000001) begin // echo
                        data_out <= data_in;
                        src_addr_out <= 32'h00000000;
                        dst_addr_out <= 32'h00000000;
                    end else if (cmd_reg == 8'b00000101) begin // sync-timer trigger
                        state <= STATE_SYNC; // Wechsel zu Sync-Zustand
                    end else begin // send/copy/to
                        data_out <= data_in;
                        src_addr_out <= src_addr_reg;
                        dst_addr_out <= dst_addr_reg;
                    end
                    valid <= 1;
                end else begin
                    data_out <= 8'h00;
                    valid <= 0;
                end
                state <= STATE_IDLE; // Zurück nach Ausführung
            end
            STATE_SYNC: begin // Parallele Verarbeitung
                if (executable) begin
                    data_out <= data_in; // Temp-Daten durchreichen
                    src_addr_out <= 32'h00000001; // SensorX
                    dst_addr_out <= 32'h00000002; // Cooler
                    valid <= 1;
                end else begin
                    data_out <= 8'h00;
                    valid <= 0;
                end
                state <= STATE_IDLE; // Zurück nach Ausführung
            end
            default: state <= STATE_IDLE; // Sicherheitsfall
        endcase
    end
endmodule

System/Archivebaldweg/Pylovara/MCSVerilog/Kernprozesse/mcs_sim.v
module mcs_sim (
    input wire clk,
    input wire [7:0] cmd,
    input wire [31:0] src_addr,
    input wire [31:0] dst_addr,
    output reg led
);
    always @(posedge clk) begin
        case (cmd)
            8'b00000001: led <= 1; // echo
            8'b00000010: led <= 1; // send
            8'b00000011: led <= 1; // copy
            8'b00000100: led <= 1; // to
            default: led <= 0;
        endcase
    end
endmodule

System/Archivebaldweg/Pylovara/MCSVerilog/Kernprozesse/mcs_sim_tb.v
module mcs_sim_tb;
    reg clk;
    reg [7:0] cmd;
    reg [31:0] src_addr;
    reg [31:0] dst_addr;
    reg [7:0] data_in;
    reg [0:0] executable;
    wire [7:0] data_out;
    wire [31:0] src_addr_out;
    wire [31:0] dst_addr_out;
    wire valid;
    wire led;

    mcs_sim dut (.clk(clk), .cmd(cmd), .src_addr(src_addr), .dst_addr(dst_addr), .led(led));
    mcs_protein protein (.clk(clk), .cmd_in(cmd), .src_addr_in(src_addr), .dst_addr_in(dst_addr),
                         .data_in(data_in), .data_out(data_out), .src_addr_out(src_addr_out),
                         .dst_addr_out(dst_addr_out), .executable(executable), .valid(valid));

    initial begin
        clk = 0;
        cmd = 8'b00000000;
        src_addr = 32'h00000000;
        dst_addr = 32'h00000000;
        data_in = 8'h00;
        executable = 1'b1;

        // Lade echo-cmd.protein-core:
        #0 cmd = 8'b00000001; src_addr = 32'h00000000; dst_addr = 32'h00000000; data_in = 8'h48; executable = 1'b1;
        // Lade send-cmd.protein-core
        #25 cmd = 8'b00000010; src_addr = 32'h00000000; dst_addr = 32'h00000010; data_in = 8'hAA; executable = 1'b1;
        // Lade copy-cmd.protein-core
        #20 cmd = 8'b00000011; src_addr = 32'h00000002; dst_addr = 32'h00000012; data_in = 8'hCC; executable = 1'b1;
        // Lade to-cmd.protein-core
        #20 cmd = 8'b00000100; src_addr = 32'h00000004; dst_addr = 32'h00000014; data_in = 8'hDD; executable = 1'b1;
        // Lade sync-timer für sync-timer.test-micro :
        #25 cmd = 8'b00000101; src_addr = 32'h00000000; dst_addr = 32'h00000000; data_in = 8'h19; executable = 1'b1; // 0x19 = 25 (Temp)

        forever #5 clk = ~clk;
    end

    initial begin
        $dumpfile("mcs_sim.vcd");
        $dumpvars(0, mcs_sim_tb);
        #120 $finish;
    end
endmodule

MCSVerilog/Kernprozesse/mcs_sim.vcd
$date
	Mon Oct 27 20:53:02 2025
$end
$version
	Icarus Verilog
$end
$timescale
	1s
$end
$scope module mcs_sim_tb $end
$var wire 1 ! valid $end
$var wire 32 " src_addr_out [31:0] $end
$var wire 1 # led $end
$var wire 32 $ dst_addr_out [31:0] $end
$var wire 8 % data_out [7:0] $end
$var reg 1 & clk $end
$var reg 8 ' cmd [7:0] $end
$var reg 8 ( data_in [7:0] $end
$var reg 32 ) dst_addr [31:0] $end
$var reg 1 * executable $end
$var reg 32 + src_addr [31:0] $end
$scope module dut $end
$var wire 1 & clk $end
$var wire 8 , cmd [7:0] $end
$var wire 32 - dst_addr [31:0] $end
$var wire 32 . src_addr [31:0] $end
$var reg 1 # led $end
$upscope $end
$scope module protein $end
$var wire 1 & clk $end
$var wire 8 / cmd_in [7:0] $end
$var wire 8 0 data_in [7:0] $end
$var wire 32 1 dst_addr_in [31:0] $end
$var wire 1 * executable $end
$var wire 32 2 src_addr_in [31:0] $end
$var parameter 3 3 STATE_CMD $end
$var parameter 3 4 STATE_DST $end
$var parameter 3 5 STATE_IDLE $end
$var parameter 3 6 STATE_SRC $end
$var parameter 3 7 STATE_SYNC $end
$var reg 8 8 cmd_reg [7:0] $end
$var reg 8 9 data_out [7:0] $end
$var reg 32 : dst_addr_out [31:0] $end
$var reg 32 ; dst_addr_reg [31:0] $end
$var reg 32 < src_addr_out [31:0] $end
$var reg 32 = src_addr_reg [31:0] $end
$var reg 3 > state [2:0] $end
$var reg 1 ! valid $end
$upscope $end
$upscope $end
$enddefinitions $end
$comment Show the parameter values. $end
$dumpall
b100 7
b10 6
b0 5
b11 4
b1 3
$end
#0
$dumpvars
b0 >
b0 =
bx <
b0 ;
bx :
bx 9
b0 8
b0 2
b0 1
b1001000 0
b1 /
b0 .
b0 -
b1 ,
b0 +
1*
b0 )
b1001000 (
b1 '
0&
bx %
bx $
x#
bx "
x!
$end
#25
b10101010 (
b10101010 0
b10000 )
b10000 -
b10000 1
b10 '
b10 ,
b10 /
#45
b11001100 (
b11001100 0
b10010 )
b10010 -
b10010 1
b10 +
b10 .
b10 2
b11 '
b11 ,
b11 /
#65
b11011101 (
b11011101 0
b10100 )
b10100 -
b10100 1
b100 +
b100 .
b100 2
b100 '
b100 ,
b100 /
#90
b11001 (
b11001 0
b0 )
b0 -
b0 1
b0 +
b0 .
b0 2
b101 '
b101 ,
b101 /
#95
0#
b11 >
b101 8
0!
1&
#100
0&
#105
1!
b0 >
1&
#110
0&
#115
b11 >
0!
1&
